{"namedChunkGroups":{"polyfill":{"name":"polyfill","assets":[{"name":"webpack-runtime-778edad192c255e9d24a.js","size":4403},{"name":"polyfill-e4c49d6c4a13b3624f99.js","size":93248}],"filteredAssets":0,"assetsSize":97651,"filteredAuxiliaryAssets":2,"auxiliaryAssetsSize":270366},"app":{"name":"app","assets":[{"name":"webpack-runtime-778edad192c255e9d24a.js","size":4403},{"name":"styles.ab07667484eaedeab20a.css","size":48813},{"name":"framework-dbb71ad78d33dc3746f8.js","size":129941},{"name":"app-4f6ab4bc5cae9512cb48.js","size":91482}],"filteredAssets":0,"assetsSize":274639,"filteredAuxiliaryAssets":12,"auxiliaryAssetsSize":872566},"component---src-pages-404-tsx":{"name":"component---src-pages-404-tsx","assets":[{"name":"commons-8ef4df94146a27c30f8b.js","size":1914882},{"name":"component---src-pages-404-tsx-8cfbc1d8dc8333875498.js","size":485}],"filteredAssets":0,"assetsSize":1915367,"filteredAuxiliaryAssets":4,"auxiliaryAssetsSize":4662284},"component---src-pages-content-tsx":{"name":"component---src-pages-content-tsx","assets":[{"name":"commons-8ef4df94146a27c30f8b.js","size":1914882},{"name":"component---src-pages-content-tsx-c6c1f6c30785723885e9.js","size":17262}],"filteredAssets":0,"assetsSize":1932144,"filteredAuxiliaryAssets":5,"auxiliaryAssetsSize":5067174},"component---src-pages-index-tsx":{"name":"component---src-pages-index-tsx","assets":[{"name":"styles.ab07667484eaedeab20a.css","size":48813},{"name":"commons-8ef4df94146a27c30f8b.js","size":1914882},{"name":"component---src-pages-index-tsx-584c9fcf3180f49b6708.js","size":114088}],"filteredAssets":0,"assetsSize":2077783,"filteredAuxiliaryAssets":17,"auxiliaryAssetsSize":7914014}},"assetsByChunkName":{"polyfill":["webpack-runtime-778edad192c255e9d24a.js","polyfill-e4c49d6c4a13b3624f99.js"],"app":["webpack-runtime-778edad192c255e9d24a.js","styles.ab07667484eaedeab20a.css","framework-dbb71ad78d33dc3746f8.js","app-4f6ab4bc5cae9512cb48.js"],"component---src-pages-404-tsx":["commons-8ef4df94146a27c30f8b.js","component---src-pages-404-tsx-8cfbc1d8dc8333875498.js"],"component---src-pages-content-tsx":["commons-8ef4df94146a27c30f8b.js","component---src-pages-content-tsx-c6c1f6c30785723885e9.js"],"component---src-pages-index-tsx":["styles.ab07667484eaedeab20a.css","commons-8ef4df94146a27c30f8b.js","component---src-pages-index-tsx-584c9fcf3180f49b6708.js"]},"childAssetsByChunkName":{}}